[{"nurse_id":0,"nurse_name":"Nurse 0","shift_preference":"morning","morning_availability_labor_day":1,"morning_availability_weekend":0,"afternoon_availability_labor_day":0,"afternoon_availability_weekend":1,"dates_off":[25],"accumulated_hours":-25,"vacations":[]},{"nurse_id":1,"nurse_name":"Nurse 1","shift_preference":"afternoon","morning_availability_labor_day":1,"morning_availability_weekend":1,"afternoon_availability_labor_day":0,"afternoon_availability_weekend":0,"dates_off":[12,19,25],"accumulated_hours":13,"vacations":[]},{"nurse_id":2,"nurse_name":"Nurse 2","shift_preference":"morning","morning_availability_labor_day":0,"morning_availability_weekend":1,"afternoon_availability_labor_day":1,"afternoon_availability_weekend":0,"dates_off":[19,11,4],"accumulated_hours":18,"vacations":[]},{"nurse_id":3,"nurse_name":"Nurse 3","shift_preference":"afternoon","morning_availability_labor_day":1,"morning_availability_weekend":1,"afternoon_availability_labor_day":0,"afternoon_availability_weekend":1,"dates_off":[4,19,11],"accumulated_hours":-16,"vacations":[]},{"nurse_id":4,"nurse_name":"Nurse 4","shift_preference":"afternoon","morning_availability_labor_day":0,"morning_availability_weekend":1,"afternoon_availability_labor_day":0,"afternoon_availability_weekend":1,"dates_off":[],"accumulated_hours":7,"vacations":[]},{"nurse_id":5,"nurse_name":"Nurse 5","shift_preference":"morning","morning_availability_labor_day":0,"morning_availability_weekend":1,"afternoon_availability_labor_day":1,"afternoon_availability_weekend":0,"dates_off":[12,5,4,11],"accumulated_hours":22,"vacations":[26,27,28,29,30,31]},{"nurse_id":6,"nurse_name":"Nurse 6","shift_preference":"morning","morning_availability_labor_day":1,"morning_availability_weekend":0,"afternoon_availability_labor_day":1,"afternoon_availability_weekend":1,"dates_off":[25],"accumulated_hours":14,"vacations":[]},{"nurse_id":7,"nurse_name":"Nurse 7","shift_preference":"morning","morning_availability_labor_day":1,"morning_availability_weekend":0,"afternoon_availability_labor_day":1,"afternoon_availability_weekend":0,"dates_off":[19,11,26],"accumulated_hours":14,"vacations":[]},{"nurse_id":8,"nurse_name":"Nurse 8","shift_preference":"morning","morning_availability_labor_day":0,"morning_availability_weekend":1,"afternoon_availability_labor_day":0,"afternoon_availability_weekend":0,"dates_off":[4,12],"accumulated_hours":2,"vacations":[5,6,7,8,9,10,11,12,13,14,15]},{"nurse_id":9,"nurse_name":"Nurse 9","shift_preference":"morning","morning_availability_labor_day":0,"morning_availability_weekend":1,"afternoon_availability_labor_day":0,"afternoon_availability_weekend":1,"dates_off":[],"accumulated_hours":-8,"vacations":[]},{"nurse_id":10,"nurse_name":"Nurse 10","shift_preference":"afternoon","morning_availability_labor_day":0,"morning_availability_weekend":0,"afternoon_availability_labor_day":1,"afternoon_availability_weekend":1,"dates_off":[5,11,4,25,18],"accumulated_hours":-3,"vacations":[]},{"nurse_id":11,"nurse_name":"Nurse 11","shift_preference":"afternoon","morning_availability_labor_day":0,"morning_availability_weekend":0,"afternoon_availability_labor_day":1,"afternoon_availability_weekend":1,"dates_off":[11,26,12],"accumulated_hours":-8,"vacations":[]},{"nurse_id":12,"nurse_name":"Nurse 12","shift_preference":"morning","morning_availability_labor_day":1,"morning_availability_weekend":0,"afternoon_availability_labor_day":1,"afternoon_availability_weekend":0,"dates_off":[12,26,11,5],"accumulated_hours":14,"vacations":[]},{"nurse_id":13,"nurse_name":"Nurse 13","shift_preference":"afternoon","morning_availability_labor_day":0,"morning_availability_weekend":1,"afternoon_availability_labor_day":0,"afternoon_availability_weekend":1,"dates_off":[11],"accumulated_hours":-3,"vacations":[]},{"nurse_id":14,"nurse_name":"Nurse 14","shift_preference":"morning","morning_availability_labor_day":0,"morning_availability_weekend":0,"afternoon_availability_labor_day":0,"afternoon_availability_weekend":1,"dates_off":[18,11,26,5,25,19],"accumulated_hours":25,"vacations":[]},{"nurse_id":15,"nurse_name":"Nurse 15","shift_preference":"afternoon","morning_availability_labor_day":1,"morning_availability_weekend":0,"afternoon_availability_labor_day":1,"afternoon_availability_weekend":0,"dates_off":[26],"accumulated_hours":14,"vacations":[]},{"nurse_id":16,"nurse_name":"Nurse 16","shift_preference":"afternoon","morning_availability_labor_day":0,"morning_availability_weekend":1,"afternoon_availability_labor_day":1,"afternoon_availability_weekend":1,"dates_off":[],"accumulated_hours":-4,"vacations":[]}]